termilighter.py
termilighter-0.0.2.dist-info/LICENSE
termilighter-0.0.2.dist-info/METADATA
termilighter-0.0.2.dist-info/WHEEL
termilighter-0.0.2.dist-info/top_level.txt
termilighter-0.0.2.dist-info/RECORD
