Metadata-Version: 2.1
Name: termilighter
Version: 0.0.2
Summary: Package for highlighting output text on terminal, and converting hex and rgb colors to xterm colors.
Home-page: https://github.com/createwithabd/highlighter
Author: Abdullah Amjad
Author-email: engineerabdullah112@gmail.com
License: License :: OSI Approved :: MIT License
Keywords: terminal-highlight,print-terminal,color-terminal,xterm-colors,conversion,rgb_to_hex,hex_to_rgb development,highlight
Classifier: Programming Language :: Python :: 3.0
Classifier: Operating System :: POSIX :: Linux
Classifier: Operating System :: Microsoft :: Windows
Classifier: License :: OSI Approved :: MIT License
Requires-Python: >=3
License-File: LICENSE
